calplus/__init__.py
calplus/base.py
calplus/client.py
calplus/exceptions.py
calplus/middlewares.py
calplus/provider.py
calplus/utils.py
calplus/validators.py
calplus/version.py
calplus/wsgi.py
calplus/cmd/cal_server.py
calplus/conf/__init__.py
calplus/conf/block_storage.py
calplus/conf/compute.py
calplus/conf/network.py
calplus/conf/object_storage.py
calplus/conf/opts.py
calplus/conf/providers.py
calplus/conf/wsgi.py
calplus/tests/__init__.py
calplus/tests/base.py
calplus/tests/fake_config_file.conf
calplus/tests/tools.py
calplus/tests/unit/__init__.py
calplus/tests/unit/conf_fixtures.py
calplus/tests/unit/test_client.py
calplus/tests/unit/test_conf_fixtures.py
calplus/tests/unit/test_connection.py
calplus/tests/unit/test_utils.py
calplus/tests/unit/test_wsgi.py
calplus/tests/unit/conf/__init__.py
calplus/tests/unit/conf/test_conf.py
calplus/tests/unit/v1/__init__.py
calplus/tests/unit/v1/test_utils.py
calplus/tests/unit/v1/block_storage/__init__.py
calplus/tests/unit/v1/compute/__init__.py
calplus/tests/unit/v1/compute/test_client.py
calplus/tests/unit/v1/compute/drivers/__init__.py
calplus/tests/unit/v1/compute/drivers/test_amazon_driver.py
calplus/tests/unit/v1/compute/drivers/test_base_driver.py
calplus/tests/unit/v1/compute/drivers/test_openstack_driver.py
calplus/tests/unit/v1/network/__init__.py
calplus/tests/unit/v1/network/test_client.py
calplus/tests/unit/v1/network/drivers/__init__.py
calplus/tests/unit/v1/network/drivers/test_amazon_driver.py
calplus/tests/unit/v1/network/drivers/test_base_driver.py
calplus/tests/unit/v1/network/drivers/test_openstack_driver.py
calplus/tests/unit/v1/object_storage/__init__.py
calplus/tests/unit/v1/object_storage/test_client.py
calplus/tests/unit/v1/object_storage/drivers/__init__.py
calplus/tests/unit/v1/object_storage/drivers/test_amazon_driver.py
calplus/tests/unit/v1/object_storage/drivers/test_base_driver.py
calplus-1.0.1.dev416.dist-info/DESCRIPTION.rst
calplus-1.0.1.dev416.dist-info/METADATA
calplus-1.0.1.dev416.dist-info/RECORD
calplus-1.0.1.dev416.dist-info/WHEEL
calplus-1.0.1.dev416.dist-info/entry_points.txt
calplus-1.0.1.dev416.dist-info/metadata.json
calplus-1.0.1.dev416.dist-info/pbr.json
calplus-1.0.1.dev416.dist-info/top_level.txt
