Metadata-Version: 2.0
Name: calplus
Version: 1.0.1.dev416
Summary: UNKNOWN
Home-page: UNKNOWN
Author: 'Kien Nguyen, Dai Dang, Nhat Hoang, Hieu LE, Binh-Minh Nguyen'
Author-email: UNKNOWN
License: 'Apache-2.0'
Keywords: 'cloud restful service'
Platform: UNKNOWN
Requires-Dist: boto3
Requires-Dist: eventlet (!=0.18.3,>=0.18.2)
Requires-Dist: falcon
Requires-Dist: gunicorn
Requires-Dist: keystoneauth1
Requires-Dist: oslo.config
Requires-Dist: oslo.context
Requires-Dist: oslo.log
Requires-Dist: oslo.utils
Requires-Dist: python-neutronclient
Requires-Dist: python-novaclient
Requires-Dist: python-swiftclient (>=3.1.0)
